py_cover_letters/__init__.py
py_cover_letters/cli.py
py_cover_letters/cli_commands/__init__.py
py_cover_letters/cli_commands/about_cmd.py
py_cover_letters/cli_commands/configuration_cmd.py
py_cover_letters/cli_commands/generate_cmd.py
py_cover_letters/cli_commands/sync_cmd.py
py_cover_letters/config.py
py_cover_letters/constants.py
py_cover_letters/db/__init__.py
py_cover_letters/db/excel.py
py_cover_letters/db/managers.py
py_cover_letters/db/models.py
py_cover_letters/db/sqlite.py
py_cover_letters/db/synchronizers.py
py_cover_letters/enums.py
py_cover_letters/exceptions.py
py_cover_letters/generators.py
py_cover_letters/mail.py
py_cover_letters/templates/Cover Letter Template.docx
py_cover_letters/templates/email_static_txt.txt
py_cover_letters/utils.py
py_cover_letters-0.3.0.dist-info/entry_points.txt
py_cover_letters-0.3.0.dist-info/LICENSE
py_cover_letters-0.3.0.dist-info/WHEEL
py_cover_letters-0.3.0.dist-info/METADATA
py_cover_letters-0.3.0.dist-info/RECORD
