Metadata-Version: 2.1
Name: py-cover-letters
Version: 0.3.0
Summary: Project to create, manage and email cover letters.
Home-page: https://github.com/luiscberrocal/py-cover-letters
License: MIT
Author: Luis C. Berrocal
Author-email: luis.berrocal.1942@gmail.com
Requires-Python: >=3.9,<4.0
Classifier: Development Status :: 2 - Pre-Alpha
Classifier: Intended Audience :: Developers
Classifier: License :: OSI Approved :: MIT License
Classifier: Natural Language :: English
Classifier: Programming Language :: Python :: 3
Classifier: Programming Language :: Python :: 3.9
Classifier: Programming Language :: Python :: 3.10
Classifier: Programming Language :: Python :: 3.11
Classifier: Programming Language :: Python :: 3
Classifier: Programming Language :: Python :: 3.10
Classifier: Programming Language :: Python :: 3.8
Classifier: Programming Language :: Python :: 3.9
Requires-Dist: click (>=8.1.3,<9.0.0)
Requires-Dist: docxtpl (>=0.16.4,<0.17.0)
Requires-Dist: openpyxl (>=3.0.10,<4.0.0)
Requires-Dist: sqlmodel (>=0.0.8,<0.0.9)
Requires-Dist: toml (>=0.10.2,<0.11.0)
Requires-Dist: twine (>=4.0.2,<5.0.0)
